djangocms_photo_gallery/README.md
djangocms_photo_gallery/__about__.py
djangocms_photo_gallery/__init__.py
djangocms_photo_gallery/admin.py
djangocms_photo_gallery/apps.py
djangocms_photo_gallery/cms_apps.py
djangocms_photo_gallery/cms_plugins.py
djangocms_photo_gallery/models.py
djangocms_photo_gallery/tests.py
djangocms_photo_gallery/urls.py
djangocms_photo_gallery/views.py
djangocms_photo_gallery/locale/de/LC_MESSAGES/django.mo
djangocms_photo_gallery/locale/de/LC_MESSAGES/django.po
djangocms_photo_gallery/migrations/0001_initial.py
djangocms_photo_gallery/migrations/__init__.py
djangocms_photo_gallery/templates/djangocms_photo_gallery/album_list.html
djangocms_photo_gallery/templates/djangocms_photo_gallery/include/album.html
djangocms_photo_gallery/templates/djangocms_photo_gallery/plugins/album.html
djangocms_photo_gallery-0.0.3.dist-info/METADATA
djangocms_photo_gallery-0.0.3.dist-info/WHEEL
djangocms_photo_gallery-0.0.3.dist-info/licenses/LICENSE.txt
djangocms_photo_gallery-0.0.3.dist-info/RECORD
