Metadata-Version: 2.1
Name: djangocms-photo-gallery
Version: 0.0.3
Project-URL: Documentation, https://github.com/MacLake/djangocms-photo-gallery#readme
Project-URL: Issues, https://github.com/MacLake/djangocms-photo-gallery/issues
Project-URL: Source, https://github.com/MacLake/djangocms-photo-gallery
Author-email: Jens-Erik Weber <Jens-Erik.Weber@passiv.de>
License-Expression: MIT
License-File: LICENSE.txt
Classifier: Development Status :: 4 - Beta
Classifier: Programming Language :: Python
Classifier: Programming Language :: Python :: 3.9
Classifier: Programming Language :: Python :: 3.10
Classifier: Programming Language :: Python :: 3.11
Classifier: Programming Language :: Python :: Implementation :: CPython
Classifier: Programming Language :: Python :: Implementation :: PyPy
Requires-Python: >=3.9
Requires-Dist: django
Requires-Dist: django-cms
Requires-Dist: django-parler
Requires-Dist: djangocms-text-ckeditor
Requires-Dist: easy-thumbnails
